{".class": "MypyFile", "_fullname": "why_dictionary", "is_partial_stub_package": false, "is_stub": false, "names": {".class": "SymbolTable", "__doc__": {".class": "SymbolTableNode", "kind": "Gdef", "node": {".class": "Var", "flags": ["is_ready"], "fullname": "why_dictionary.__doc__", "name": "__doc__", "type": "builtins.str"}}, "__file__": {".class": "SymbolTableNode", "kind": "Gdef", "node": {".class": "Var", "flags": ["is_ready"], "fullname": "why_dictionary.__file__", "name": "__file__", "type": "builtins.str"}}, "__name__": {".class": "SymbolTableNode", "kind": "Gdef", "node": {".class": "Var", "flags": ["is_ready"], "fullname": "why_dictionary.__name__", "name": "__name__", "type": "builtins.str"}}, "__package__": {".class": "SymbolTableNode", "kind": "Gdef", "node": {".class": "Var", "flags": ["is_ready"], "fullname": "why_dictionary.__package__", "name": "__package__", "type": "builtins.str"}}, "bits": {".class": "SymbolTableNode", "kind": "Gdef", "node": {".class": "FuncDef", "arg_kinds": [0], "arg_names": ["a"], "flags": [], "fullname": "why_dictionary.bits", "name": "bits", "type": null}}, "key": {".class": "SymbolTableNode", "kind": "Gdef", "node": {".class": "Var", "flags": [], "fullname": "why_dictionary.key", "name": "key", "type": "builtins.object"}}}, "path": "/home/msr/books/python/python_progs/real_python_tutorails/dictionarys/why_dictionary.py"}