[
  {
    "userId": 5,
    "title": "suscipit qui totam",
    "completed": true,
    "id": 81
  },
  {
    "userId": 5,
    "title": "quidem at rerum quis ex aut sit quam",
    "completed": true,
    "id": 83
  },
  {
    "userId": 5,
    "title": "et quia ad iste a",
    "completed": true,
    "id": 85
  },
  {
    "userId": 5,
    "title": "incidunt ut saepe autem",
    "completed": true,
    "id": 86
  },
  {
    "userId": 5,
    "title": "laudantium quae eligendi consequatur quia et vero autem",
    "completed": true,
    "id": 87
  },
  {
    "userId": 5,
    "title": "sequi ut omnis et",
    "completed": true,
    "id": 89
  },
  {
    "userId": 5,
    "title": "molestiae nisi accusantium tenetur dolorem et",
    "completed": true,
    "id": 90
  },
  {
    "userId": 5,
    "title": "nulla quis consequatur saepe qui id expedita",
    "completed": true,
    "id": 91
  },
  {
    "userId": 5,
    "title": "in omnis laboriosam",
    "completed": true,
    "id": 92
  },
  {
    "userId": 5,
    "title": "odio iure consequatur molestiae quibusdam necessitatibus quia sint",
    "completed": true,
    "id": 93
  },
  {
    "userId": 5,
    "title": "vel nihil et molestiae iusto assumenda nemo quo ut",
    "completed": true,
    "id": 95
  },
  {
    "userId": 5,
    "title": "debitis accusantium ut quo facilis nihil quis sapiente necessitatibus",
    "completed": true,
    "id": 98
  },
  {
    "userId": 10,
    "title": "inventore saepe cumque et aut illum enim",
    "completed": true,
    "id": 182
  },
  {
    "userId": 10,
    "title": "omnis nulla eum aliquam distinctio",
    "completed": true,
    "id": 183
  },
  {
    "userId": 10,
    "title": "vel non beatae est",
    "completed": true,
    "id": 188
  },
  {
    "userId": 10,
    "title": "culpa eius et voluptatem et",
    "completed": true,
    "id": 189
  },
  {
    "userId": 10,
    "title": "accusamus sint iusto et voluptatem exercitationem",
    "completed": true,
    "id": 190
  },
  {
    "userId": 10,
    "title": "temporibus atque distinctio omnis eius impedit tempore molestias pariatur",
    "completed": true,
    "id": 191
  },
  {
    "userId": 10,
    "title": "rerum debitis voluptatem qui eveniet tempora distinctio a",
    "completed": true,
    "id": 193
  },
  {
    "userId": 10,
    "title": "rerum ex veniam mollitia voluptatibus pariatur",
    "completed": true,
    "id": 195
  },
  {
    "userId": 10,
    "title": "consequuntur aut ut fugit similique",
    "completed": true,
    "id": 196
  },
  {
    "userId": 10,
    "title": "dignissimos quo nobis earum saepe",
    "completed": true,
    "id": 197
  },
  {
    "userId": 10,
    "title": "quis eius est sint explicabo",
    "completed": true,
    "id": 198
  },
  {
    "userId": 10,
    "title": "numquam repellendus a magnam",
    "completed": true,
    "id": 199
  }
]